modal_migrate/__about__.py
modal_migrate/__init__.py
modal_migrate/__main__.py
modal_migrate/main.py
modal_migrate-0.1.1.dist-info/METADATA
modal_migrate-0.1.1.dist-info/WHEEL
modal_migrate-0.1.1.dist-info/entry_points.txt
modal_migrate-0.1.1.dist-info/licenses/LICENSE.txt
modal_migrate-0.1.1.dist-info/RECORD
