Metadata-Version: 2.3
Name: modal-migrate
Version: 0.1.1
Summary: Migrate Modal codebases automatically.
Project-URL: Documentation, https://github.com/modal-labs/modal-migrate#readme
Project-URL: Issues, https://github.com/modal-labs/modal-migrate/issues
Project-URL: Source, https://github.com/modal-labs/modal-migrate
Author-email: Eric Zhang <ekzhang1@gmail.com>
License-Expression: MIT
License-File: LICENSE.txt
Classifier: Development Status :: 4 - Beta
Classifier: Programming Language :: Python
Classifier: Programming Language :: Python :: 3.8
Classifier: Programming Language :: Python :: 3.9
Classifier: Programming Language :: Python :: 3.10
Classifier: Programming Language :: Python :: 3.11
Classifier: Programming Language :: Python :: 3.12
Classifier: Programming Language :: Python :: Implementation :: CPython
Classifier: Programming Language :: Python :: Implementation :: PyPy
Requires-Python: >=3.8
Requires-Dist: libcst<2,>=1
Requires-Dist: rich>=12
Requires-Dist: typer>=0.9
